aioodbc/__init__.py
aioodbc/_version.py
aioodbc/connection.py
aioodbc/cursor.py
aioodbc/log.py
aioodbc/pool.py
aioodbc/utils.py
aioodbc-0.5.0.dist-info/LICENSE
aioodbc-0.5.0.dist-info/METADATA
aioodbc-0.5.0.dist-info/WHEEL
aioodbc-0.5.0.dist-info/top_level.txt
aioodbc-0.5.0.dist-info/RECORD
