Metadata-Version: 2.1
Name: aioodbc
Version: 0.5.0
Summary: ODBC driver for asyncio.
Home-page: https://github.com/aio-libs/aioodbc
Download-URL: https://pypi.python.org/pypi/aioodbc
Author: Nikolay Novik
Author-email: nickolainovik@gmail.com
License: Apache 2
Project-URL: Website, https://github.com/jettify/uddsketch
Project-URL: Documentation, https://uddsketch.readthedocs.io
Project-URL: Issues, https://github.com/jettify/uddsketch/issues
Platform: POSIX
Classifier: License :: OSI Approved :: Apache Software License
Classifier: Intended Audience :: Developers
Classifier: Programming Language :: Python :: 3
Classifier: Programming Language :: Python :: 3.7
Classifier: Programming Language :: Python :: 3.8
Classifier: Programming Language :: Python :: 3.9
Classifier: Programming Language :: Python :: 3.10
Classifier: Programming Language :: Python :: 3.11
Classifier: Programming Language :: Python :: 3.12
Classifier: Operating System :: POSIX
Classifier: Environment :: Web Environment
Classifier: Development Status :: 3 - Alpha
Classifier: Topic :: Database
Classifier: Topic :: Database :: Front-Ends
Classifier: Framework :: AsyncIO
Requires-Python: >=3.7
License-File: LICENSE
Requires-Dist: pyodbc>=5.0.1
